README.md
setup.cfg
setup.py
datapreprocessor/__init__.py
datapreprocessor/categoricdata.py
datapreprocessor/engine.py
datapreprocessor/metadata.py
datapreprocessor/missingdata.py
datapreprocessor/scaling.py
datapreprocessor/shift.py
datapreprocessor.egg-info/PKG-INFO
datapreprocessor.egg-info/SOURCES.txt
datapreprocessor.egg-info/dependency_links.txt
datapreprocessor.egg-info/not-zip-safe
datapreprocessor.egg-info/top_level.txt