Metadata-Version: 1.0
Name: datapreprocessor
Version: 0.2.1
Summary: A tool for preprocessing data for data analasys and machine learning.
Home-page: https://github.com/jovicigor/DataPreprocessor
Author: Igor Jovic
Author-email: jovic.i24@gmail.com
License: MIT
Platform: UNKNOWN
